jax_ml_stack/__init__.py
jax_ml_stack-0.0.0.dist-info/LICENSE
jax_ml_stack-0.0.0.dist-info/METADATA
jax_ml_stack-0.0.0.dist-info/WHEEL
jax_ml_stack-0.0.0.dist-info/top_level.txt
jax_ml_stack-0.0.0.dist-info/RECORD
