Metadata-Version: 2.1
Name: jax_ml_stack
Version: 0.0.0
Author-email: jax_ml_stack authors <jax_ml_stack@google.com>
License: 
Project-URL: homepage, https://github.com/jax-ml/jax_ml_stack
Project-URL: repository, https://github.com/jax-ml/jax_ml_stack
Classifier: Programming Language :: Python :: 3
Classifier: Programming Language :: Python :: 3 :: Only
Classifier: License :: OSI Approved :: Apache Software License
Classifier: Intended Audience :: Science/Research
License-File: LICENSE
Requires-Dist: jax ==0.4.31
Requires-Dist: flax ==0.8.5
Requires-Dist: optax ==0.2.3
Requires-Dist: orbax ==0.1.9
Provides-Extra: dev
Requires-Dist: pytest ; extra == 'dev'
Requires-Dist: pytest-xdist ; extra == 'dev'
